{
    "Acil": [
        "acil.mp4"
    ],
    "Burası büyük bir hastane.": [
        "bura.mp4",
        "büyük.mp4",
        "bir.mp4",
        "hastane.mp4"
    ],
    "Hastanede birçok bölüm var:": [
        "hastane.mp4",
        "birçok.gif",
        "bölüm.mp4",
        "var.mp4"
    ],
    "Birinci katta kulak, burun, boğaz;": [
        "birinci.mp4",
        "kat.mp4",
        "kulak.mp4",
        "burun.mp4",
        "boğaz.mp4"
    ],
    "ikinci katta iç hastalıkları ve göz;": [
        "ikinci.mp4",
        "kat.mp4",
        "iç.mp4",
        "hastalık.mp4",
        "ve.mp4",
        "göz.mp4"
    ],
    "üçüncü katta alerji ve beslenme;": [
        "üçüncü.mp4",
        "kat.mp4",
        "alerji.mp4",
        "ve.mp4",
        "beslemek.mp4"
    ],
    "dördüncü katta çocuk hastalıkları… Üst katlarda hasta odaları var.": [
        "dördüncü.mp4",
        "kat.mp4",
        "çocuk.mp4",
        "hastalık.mp4",
        "üst.mp4",
        "kat.mp4",
        "hasta.mp4",
        "oda.mp4",
        "var.mp4"
    ],
    "Hastanede doktorlar, hemşireler ve hasta bakıcılar çalışıyor.": [
        "hastane.mp4",
        "doktor.mp4",
        "hemşire.mp4",
        "ve.mp4",
        "hasta_bakıcı.gif",
        "çalışmak.mp4"
    ],
    "Buraya çok fazla acil hasta geliyor.": [
        "bura.mp4",
        "çok.mp4",
        "fazla.mp4",
        "acil.mp4",
        "hasta.mp4",
        "gelmek.mp4"
    ],
    "Acil servis yan binada.": [
        "acil.mp4",
        "servis.mp4",
        "yan.mp4",
        "bina.mp4"
    ],
    "Acil servisin önünde her zaman ambulanslar var.": [
        "acil.mp4",
        "servis.mp4",
        "ön.mp4",
        "her.mp4",
        "zaman.mp4",
        "ambulans.mp4",
        "var.mp4"
    ],
    "Ambulanslar hastaları hastaneye getiriyorlar.": [
        "ambulans.mp4",
        "hasta.mp4",
        "hastane.mp4",
        "getirmek.mp4"
    ],
    "Acil servisin önü çok kalabalık oluyor.": [
        "acil.mp4",
        "servis.mp4",
        "ön.mp4",
        "çok.mp4",
        "kalabalık.mp4",
        "olmak.mp4"
    ],
    "Hastalar, hasta yakınları acil servise giriyorlar.": [
        "hasta.mp4",
        "hasta.mp4",
        "yakın.mp4",
        "acil.mp4",
        "servis.mp4",
        "girmek.mp4"
    ],
    "Herkes çok telaşlı, meraklı, üzgün ve yorgun.": [
        "herkes.mp4",
        "çok.mp4",
        "telaş.gif",
        "merak.mp4",
        "üzgün.mp4",
        "ve.mp4",
        "yorgun.mp4"
    ],
    "Doktor Levent bu gece hastanede nöbetçiydi.": [
        "doktor.mp4",
        "l.gif",
        "e.gif",
        "v.gif",
        "e.gif",
        "n.gif",
        "t.gif",
        "bu.mp4",
        "gece.mp4",
        "hastane.mp4",
        "nöbet.mp4"
    ],
    "O, çok yoruldu.": [
        "o.mp4",
        "çok.mp4",
        "yormak.mp4"
    ],
    "Çünkü sabaha kadar acilde çok çalıştı.": [
        "çünkü.mp4",
        "sabah.mp4",
        "kadar.mp4",
        "acil.mp4",
        "çok.mp4",
        "çalışmak.mp4"
    ],
    "Hastanenin acil servisi çok yorucu.": [
        "hastane.mp4",
        "acil.mp4",
        "servis.mp4",
        "çok.mp4",
        "yormak.mp4"
    ],
    "Acile trafik kazaları, ev kazaları.": [
        "acil.mp4",
        "trafik.mp4",
        "kaza.mp4",
        "ev.mp4",
        "kaza.mp4"
    ],
    "çok çeşitli acil hasta geliyor.": [
        "çok.mp4",
        "çeşit.mp4",
        "acil.mp4",
        "hasta.mp4",
        "gelmek.mp4"
    ],
    "Normal bir günde muayene kolay.": [
        "normal.mp4",
        "bir.mp4",
        "gün.mp4",
        "muayene.mp4",
        "kolay.mp4"
    ],
    "Hastalar genelde grip, ateş, tansiyon ve soğuk algınlığı için geliyorlar.": [
        "hasta.mp4",
        "genelde.mp4",
        "grip.gif",
        "ateş.mp4",
        "tansiyon.mp4",
        "ve.mp4",
        "soğuk_algınlığı.mp4",
        "için.mp4",
        "gelmek.mp4"
    ],
    "Ama acil çok farklı.": [
        "ama.mp4",
        "acil.mp4",
        "çok.mp4",
        "fark.mp4"
    ],
    "Birçok yaralı insan var.": [
        "birçok.gif",
        "yara.mp4",
        "insan.mp4",
        "var.mp4"
    ],
    "Gece yine trafik kazası oldu.": [
        "gece.mp4",
        "yine.gif",
        "trafik.mp4",
        "kaza.mp4",
        "olmak.mp4"
    ],
    "Doktor Levent birkaç hastaya baktı.": [
        "doktor.mp4",
        "l.gif",
        "e.gif",
        "v.gif",
        "e.gif",
        "n.gif",
        "t.gif",
        "birkaç.mp4",
        "hasta.mp4",
        "bakmak.mp4"
    ],
    "Onların yaralarını sardı.": [
        "o.mp4",
        "yara.mp4",
        "sarmak.mp4"
    ],
    "Bir hastayı ameliyat etti.": [
        "bir.mp4",
        "hasta.mp4",
        "ameliyat.mp4",
        "et.mp4"
    ],
    "Ameliyat sabaha doğru bitti.": [
        "ameliyat.mp4",
        "sabah.mp4",
        "doğru.mp4",
        "bitmek.mp4"
    ],
    "Ameliyattan sonra kendine bir kahve aldı.": [
        "ameliyat.mp4",
        "sonra.mp4",
        "kendi.mp4",
        "bir.mp4",
        "kahve.mp4",
        "almak.mp4"
    ],
    "Biraz dinlenmek istedi.": [
        "biraz.mp4",
        "dinlenmek.mp4",
        "istemek.mp4"
    ],
    "Odasındaki koltuğa oturdu, ayaklarını sandalyeye uzattı.": [
        "oda.mp4",
        "koltuk.mp4",
        "oturmak.mp4",
        "ayak.mp4",
        "sandalye.mp4",
        "uzamak.mp4"
    ],
    "Bütün gece hastalarla ilgilendi, şimdi kendine zaman ayırıyor.": [
        "bütün.mp4",
        "gece.mp4",
        "hasta.mp4",
        "ilgilenmek.mp4",
        "şimdi.mp4",
        "kendi.mp4",
        "zaman.mp4",
        "ayırmak.mp4"
    ],
    "Kahvesinden bir yudum içti.": [
        "kahve.mp4",
        "bir.mp4",
        "yudum.mp4",
        "içmek.mp4"
    ],
    "Genç bir doktor kapıyı çaldı.": [
        "genç.mp4",
        "bir.mp4",
        "doktor.mp4",
        "kapı.mp4",
        "çalmak.mp4"
    ],
    "— Levent Bey, bir çocuk geldi.": [
        "l.gif",
        "e.gif",
        "v.gif",
        "e.gif",
        "n.gif",
        "t.gif",
        "bey.mp4",
        "bir.mp4",
        "çocuk.mp4",
        "gelmek.mp4"
    ],
    "Ayağında bir problem var.": [
        "ayak.mp4",
        "bir.mp4",
        "problem.mp4",
        "var.mp4"
    ],
    "Servis görevlisi ve şoförle birlikte geldi.": [
        "servis.mp4",
        "görev.mp4",
        "ve.mp4",
        "şoför.gif",
        "birlikte.mp4",
        "gelmek.mp4"
    ],
    "Kızın yanında kimlik yok.": [
        "kız.mp4",
        "yan.mp4",
        "kimlik.mp4",
        "yok.mp4"
    ],
    "Sırtında okul çantası var.": [
        "sırt.mp4",
        "okul.mp4",
        "çanta.mp4",
        "var.mp4"
    ],
    "Galiba okula gidiyor.": [
        "galiba.mp4",
        "okul.mp4",
        "gitmek.mp4"
    ],
    "Doktor Levent o gece çok hastaya baktı.": [
        "doktor.mp4",
        "l.gif",
        "e.gif",
        "v.gif",
        "e.gif",
        "n.gif",
        "t.gif",
        "o.mp4",
        "gece.mp4",
        "çok.mp4",
        "hasta.mp4",
        "bakmak.mp4"
    ],
    "Çok yorgundu.": [
        "çok.mp4",
        "yorgun.mp4"
    ],
    "Genç doktora döndü:": [
        "genç.mp4",
        "doktor.mp4",
        "dönmek.mp4"
    ],
    "— Hasta konuşuyor mu?": [
        "hasta.mp4",
        "konuşmak.mp4",
        "mu.mp4"
    ],
    "— Evet hocam.": [
        "evet.mp4",
        "hoca.mp4"
    ],
    "— Hastanın durumu ne?": [
        "hasta.mp4",
        "durum.mp4",
        "ne.mp4"
    ],
    "— Ayağında ve kollarında küçük yaralar var.": [
        "ayak.mp4",
        "ve.mp4",
        "kol.mp4",
        "küçük.mp4",
        "yara.mp4",
        "var.mp4"
    ],
    "— Hım!": [
        "h.gif",
        "ı.gif",
        "m.gif"
    ],
    "Demek yaralar küçük.": [
        "demek.mp4",
        "yara.mp4",
        "küçük.mp4"
    ],
    "Hastaya sen bakabilirsin.": [
        "hasta.mp4",
        "sen.mp4",
        "bakmak.mp4"
    ],
    "— Peki Levent Bey.": [
        "peki.mp4",
        "l.gif",
        "e.gif",
        "v.gif",
        "e.gif",
        "n.gif",
        "t.gif",
        "bey.mp4"
    ],
    "Genç doktor odadan çıktı.": [
        "genç.mp4",
        "doktor.mp4",
        "oda.mp4",
        "çıkmak.mp4"
    ],
    "O, çok sevindi.": [
        "o.mp4",
        "çok.mp4",
        "sevinmek.mp4"
    ],
    "Doktorlar onlara bu konuda daha önce izin vermedi.": [
        "doktor.mp4",
        "o.mp4",
        "bu.mp4",
        "konu.mp4",
        "daha.mp4",
        "önce.mp4",
        "izin_vermek.mp4"
    ],
    "Hasta tedavi etmek genç doktorlar için tecrübe oluyor.": [
        "hasta.mp4",
        "tedavi_etmek.gif",
        "genç.mp4",
        "doktor.mp4",
        "için.mp4",
        "tecrübe.mp4",
        "olmak.mp4"
    ],
    "Şimdi bir hastası var.": [
        "şimdi.mp4",
        "bir.mp4",
        "hasta.mp4",
        "var.mp4"
    ],
    "Zor bir hasta değil.": [
        "zor.mp4",
        "bir.mp4",
        "hasta.mp4",
        "değil.mp4"
    ],
    "Hemen hastanın yanına gitti.": [
        "hemen.mp4",
        "hasta.mp4",
        "yan.mp4",
        "gitmek.mp4"
    ],
    "Servis görevlisine ve şoföre:": [
        "servis.mp4",
        "görev.mp4",
        "ve.mp4",
        "şoför.gif"
    ],
    "— Siz dışarıda bekleyin, dedi.": [
        "siz.mp4",
        "dışarı.mp4",
        "beklemek.mp4",
        "demek.mp4"
    ],
    "— Merhaba küçük kız.": [
        "merhaba.mp4",
        "küçük.mp4",
        "kız.mp4"
    ],
    "Senin adın ne?": [
        "sen.mp4",
        "ad.mp4",
        "ne.mp4"
    ],
    "— Filiz.": [
        "f.gif",
        "i.gif",
        "l.gif",
        "i.gif",
        "z.gif"
    ],
    "Filiz ağlıyor.": [
        "f.gif",
        "i.gif",
        "l.gif",
        "i.gif",
        "z.gif",
        "ağlamak.mp4"
    ],
    "Genç doktor:": [
        "genç.mp4",
        "doktor.mp4"
    ],
    "— Korkma, sana yardım için geldim.": [
        "korkmak.mp4",
        "sen.mp4",
        "yardım.mp4",
        "için.mp4",
        "gelmek.mp4"
    ],
    "Sen kaç yaşındasın?": [
        "sen.mp4",
        "kaç.mp4",
        "yaş.mp4"
    ],
    "— Altı.": [
        "altı.mp4"
    ],
    "Yine ağlıyor.": [
        "yine.gif",
        "ağlamak.mp4"
    ],
    "Annesini ve babasını istiyor.": [
        "anne.mp4",
        "ve.mp4",
        "baba.mp4",
        "istemek.mp4"
    ],
    "— Ben annemi ve babamı istiyorum.": [
        "ben.mp4",
        "anne.mp4",
        "ve.mp4",
        "baba.mp4",
        "istemek.mp4"
    ],
    "— Tamam canım, onlar da gelecekler ama şimdi ayağına bakalım.": [
        "tamam.mp4",
        "can.mp4",
        "o.mp4",
        "gelecek.mp4",
        "ama.mp4",
        "şimdi.mp4",
        "ayak.mp4",
        "bakmak.mp4"
    ],
    "— Anneeee!": [
        "e.gif",
        "e.gif"
    ],
    "Ben annemi istiyorum!": [
        "ben.mp4",
        "anne.mp4",
        "istemek.mp4"
    ],
    "— Tamam, anneni bulacağız.": [
        "tamam.mp4",
        "anne.mp4",
        "bulmak.mp4"
    ],
    "— Soyadın ne?": [
        "soyadı.mp4",
        "ne.mp4"
    ],
    "— Babanın adı ne?": [
        "baba.mp4",
        "ad.mp4",
        "ne.mp4"
    ],
    "— Tamam, konuşmuyorsun.": [
        "tamam.mp4",
        "konuşmak.mp4"
    ],
    "Problem yok.": [
        "problem.mp4",
        "yok.mp4"
    ],
    "Önce ayağına bakalım.": [
        "önce.mp4",
        "ayak.mp4",
        "bakmak.mp4"
    ],
    "Ayak parmaklarını tutalım.": [
        "ayak.mp4",
        "parmak.mp4",
        "tutmak.mp4"
    ],
    "Şimdi ağrıyor mu?": [
        "şimdi.mp4",
        "ağrımak.mp4",
        "mu.mp4"
    ],
    "— Evet, ağrıyor.": [
        "evet.mp4",
        "ağrımak.mp4"
    ],
    "— Peki, şimdi kolunu kaldıralım.": [
        "peki.mp4",
        "şimdi.mp4",
        "kol.mp4",
        "kaldırmak.mp4"
    ],
    "Kolun ağrıyor mu?": [
        "kol.mp4",
        "ağrımak.mp4",
        "mu.mp4"
    ],
    "— Hayır, ağrımıyor.": [
        "hayır.mp4",
        "ağrımak.mp4"
    ],
    "Filiz biraz korkuyor.": [
        "f.gif",
        "i.gif",
        "l.gif",
        "i.gif",
        "z.gif",
        "biraz.mp4",
        "korkmak.mp4"
    ],
    "Genç doktor önce Filiz’in ayağına baktı.": [
        "genç.mp4",
        "doktor.mp4",
        "önce.mp4",
        "f.gif",
        "i.gif",
        "l.gif",
        "i.gif",
        "z.gif",
        "ayak.mp4",
        "bakmak.mp4"
    ],
    "Filiz’in ayağı şiş.": [
        "f.gif",
        "i.gif",
        "l.gif",
        "i.gif",
        "z.gif",
        "ayak.mp4",
        "şişe.mp4"
    ],
    "Röntgen çekmek gerekiyor.": [
        "röntgen.mp4",
        "çekmek.mp4",
        "gerekmek.mp4"
    ],
    "Hemen hemşirelerden röntgen istedi.": [
        "hemen.mp4",
        "hemşire.mp4",
        "röntgen.mp4",
        "istemek.mp4"
    ],
    "Onlar Filiz’i radyoloji katına götürdü.": [
        "o.mp4",
        "f.gif",
        "i.gif",
        "l.gif",
        "i.gif",
        "z.gif",
        "r.gif",
        "a.mp4",
        "d.gif",
        "y.gif",
        "o.mp4",
        "l.gif",
        "o.mp4",
        "j.gif",
        "i.gif",
        "kat.mp4",
        "götürmek.mp4"
    ],
    "Röntgen çektiler.": [
        "röntgen.mp4",
        "çekmek.mp4"
    ],
    "Genç doktor röntgene baktı.": [
        "genç.mp4",
        "doktor.mp4",
        "röntgen.mp4",
        "bakmak.mp4"
    ],
    "Küçük kızın ayağında bir kırık vardı.": [
        "küçük.mp4",
        "kız.mp4",
        "ayak.mp4",
        "bir.mp4",
        "kırıkkale.gif",
        "var.mp4"
    ],
    "Genç doktor biraz düşündü.": [
        "genç.mp4",
        "doktor.mp4",
        "biraz.mp4",
        "düşünmek.mp4"
    ],
    "Doktor Levent’in yanına gitti.": [
        "doktor.mp4",
        "l.gif",
        "e.gif",
        "v.gif",
        "e.gif",
        "n.gif",
        "t.gif",
        "yan.mp4",
        "gitmek.mp4"
    ],
    "Kapıyı çaldı:": [
        "kapı.mp4",
        "çalmak.mp4"
    ],
    "—  Levent  Bey,  affedersiniz.": [
        "l.gif",
        "e.gif",
        "v.gif",
        "e.gif",
        "n.gif",
        "t.gif",
        "bey.mp4",
        "affetmek.mp4"
    ],
    "Küçük  kızın  bacağında  kırık  var.": [
        "küçük.mp4",
        "kız.mp4",
        "bacak.mp4",
        "kırıkkale.gif",
        "var.mp4"
    ],
    "Ben daha önce hiç kırık tedavi etmedim.": [
        "ben.mp4",
        "daha.mp4",
        "önce.mp4",
        "hiç.mp4",
        "kırıkkale.gif",
        "tedavi_etmek.gif"
    ],
    "Doktor Levent şaşırdı.": [
        "doktor.mp4",
        "l.gif",
        "e.gif",
        "v.gif",
        "e.gif",
        "n.gif",
        "t.gif",
        "şaşırmak.mp4"
    ],
    "Ayak röntgenine baktı:": [
        "ayak.mp4",
        "röntgen.mp4",
        "bakmak.mp4"
    ],
    "— Erhancığım basit bir kırık, sen çok rahat tedavi edersin.": [
        "e.gif",
        "r.gif",
        "h.gif",
        "a.mp4",
        "n.gif",
        "basit.mp4",
        "bir.mp4",
        "kırıkkale.gif",
        "sen.mp4",
        "çok.mp4",
        "rahat.mp4",
        "tedavi_etmek.gif"
    ],
    "Ben sana güveniyorum.": [
        "ben.mp4",
        "sen.mp4",
        "güvenmek.mp4"
    ],
    "Küçük kızın yanına gitti.": [
        "küçük.mp4",
        "kız.mp4",
        "yan.mp4",
        "gitmek.mp4"
    ],
    "Hasta bakıcılar ona oyuncak verdi ama kız oyuncağı istemedi.": [
        "hasta_bakıcı.gif",
        "o.mp4",
        "oyuncak.mp4",
        "vermek.mp4",
        "ama.mp4",
        "kız.mp4",
        "oyuncak.mp4",
        "istemek.mp4"
    ],
    "Genç doktor masadaki başka bir oyuncağı ona verdi:": [
        "genç.mp4",
        "doktor.mp4",
        "masa.mp4",
        "başka.mp4",
        "bir.mp4",
        "oyuncak.mp4",
        "o.mp4",
        "vermek.mp4"
    ],
    "— Filizciğim, şimdi bitiyor.": [
        "f.gif",
        "i.gif",
        "l.gif",
        "i.gif",
        "z.gif",
        "şimdi.mp4",
        "bitmek.mp4"
    ],
    "Lütfen sakin ol, korkma, oyuncağı sıkı tut.": [
        "lütfen.mp4",
        "sakin.mp4",
        "olmak.mp4",
        "korkmak.mp4",
        "oyuncak.mp4",
        "sıkılmak.mp4",
        "tutmak.mp4"
    ],
    "— Ben annemi istiyorum.": [
        "ben.mp4",
        "anne.mp4",
        "istemek.mp4"
    ],
    "— Tamam, bu arada biraz konuşalım.": [
        "tamam.mp4",
        "bu.mp4",
        "ara.mp4",
        "biraz.mp4",
        "konuşmak.mp4"
    ],
    "Annenin adı ne?": [
        "anne.mp4",
        "ad.mp4",
        "ne.mp4"
    ],
    "Genç doktor kızın bacağını alçıya alıyor ve onunla konuşuyor:": [
        "genç.mp4",
        "doktor.mp4",
        "kız.mp4",
        "bacak.mp4",
        "alçı.mp4",
        "almak.mp4",
        "ve.mp4",
        "o.mp4",
        "konuşmak.mp4"
    ],
    "— Annemin adı Tuğba.": [
        "anne.mp4",
        "ad.mp4",
        "t.gif",
        "u.gif",
        "ğ.gif",
        "b.mp4",
        "b.gif",
        "a.mp4"
    ],
    "— Peki, annen ne iş yapıyor?": [
        "peki.mp4",
        "anne.mp4",
        "ne.mp4",
        "iş.mp4",
        "yapmak.mp4"
    ],
    "— Annem öğretmen.": [
        "anne.mp4",
        "öğretmen.mp4"
    ],
    "— Güzel.": [
        "güzel.mp4"
    ],
    "Annen şimdi okulda mı?": [
        "anne.mp4",
        "şimdi.mp4",
        "okul.mp4",
        "mı.mp4"
    ],
    "— Evet.": [
        "evet.mp4"
    ],
    "— Telefon numarasını biliyor musun?": [
        "telefon.mp4",
        "numara.mp4",
        "bilmek.mp4",
        "mu.mp4"
    ],
    "— Hayır, bilmiyorum.": [
        "hayır.mp4",
        "bilmek.mp4"
    ],
    "Adresimizi biliyorum.": [
        "adres.mp4",
        "bilmek.mp4"
    ],
    "— Tamam, bize adresi ver.": [
        "tamam.mp4",
        "biz.mp4",
        "adres.mp4",
        "vermek.mp4"
    ],
    "Anneni buraya getirelim.": [
        "anne.mp4",
        "bura.mp4",
        "getirmek.mp4"
    ],
    "— Adres çantamda.": [
        "adres.mp4",
        "çanta.mp4"
    ],
    "— Aa, bak!": [
        "a.mp4",
        "a.mp4",
        "bakmak.mp4"
    ],
    "Bu çok güzel.": [
        "bu.mp4",
        "çok.mp4",
        "güzel.mp4"
    ],
    "Şimdi anneni buraya çağıralım.": [
        "şimdi.mp4",
        "anne.mp4",
        "bura.mp4",
        "çağırmak.mp4"
    ],
    "Genç doktor, oradaki hasta bakıcılara adresi verdi.": [
        "genç.mp4",
        "doktor.mp4",
        "ora.mp4",
        "hasta_bakıcı.gif",
        "adres.mp4",
        "vermek.mp4"
    ],
    "— Lütfen, annesine ulaşalım.": [
        "lütfen.mp4",
        "anne.mp4",
        "ulaşmak.mp4"
    ],
    "— Tamam, dedi hasta bakıcı.": [
        "tamam.mp4",
        "demek.mp4",
        "hasta_bakıcı.gif"
    ],
    "Acil odasından hızla çıktı.": [
        "acil.mp4",
        "oda.mp4",
        "hız.mp4",
        "çıkmak.mp4"
    ],
    "Genç doktor, küçük kızın tedavisini tamamladı.": [
        "genç.mp4",
        "doktor.mp4",
        "küçük.mp4",
        "kız.mp4",
        "tedavi.gif",
        "t.gif",
        "a.mp4",
        "m.gif",
        "a.mp4",
        "m.gif",
        "l.gif",
        "a.mp4",
        "m.gif",
        "a.mp4",
        "k.gif"
    ],
    "Biraz terledi.": [
        "biraz.mp4",
        "terlemek.mp4"
    ],
    "Bu iş onun için zordu.": [
        "bu.mp4",
        "iş.mp4",
        "o.mp4",
        "için.mp4",
        "zor.mp4"
    ],
    "Hemşireler ona yardım ettiler.": [
        "hemşire.mp4",
        "o.mp4",
        "yardım.mp4",
        "et.mp4"
    ],
    "Tam o anda kapıdan Doktor Levent girdi.": [
        "tam.mp4",
        "o.mp4",
        "an.mp4",
        "kapı.mp4",
        "doktor.mp4",
        "l.gif",
        "e.gif",
        "v.gif",
        "e.gif",
        "n.gif",
        "t.gif",
        "g.gif",
        "i.gif",
        "r.gif",
        "d.gif",
        "i.gif"
    ],
    "Levent Bey çok şaşırdı.": [
        "l.gif",
        "e.gif",
        "v.gif",
        "e.gif",
        "n.gif",
        "t.gif",
        "bey.mp4",
        "çok.mp4",
        "şaşırmak.mp4"
    ],
    "Hemen küçük kıza sarıldı.": [
        "hemen.mp4",
        "küçük.mp4",
        "kız.mp4",
        "sarmak.mp4"
    ],
    "— Kızım, sana ne oldu böyle?": [
        "kız.mp4",
        "sen.mp4",
        "ne.mp4",
        "olmak.mp4",
        "böyle.mp4"
    ],
    "— Babaaaa!": [
        "a.mp4",
        "a.mp4"
    ],
    "Küçük kız ağlıyor.": [
        "küçük.mp4",
        "kız.mp4",
        "ağlamak.mp4"
    ],
    "— Tamam, sakin ol canım.": [
        "tamam.mp4",
        "sakin.mp4",
        "olmak.mp4",
        "can.mp4"
    ],
    "Genç doktor çok şaşırdı.": [
        "genç.mp4",
        "doktor.mp4",
        "çok.mp4",
        "şaşırmak.mp4"
    ],
    "Odadaki herkes çok şaşırdı.": [
        "oda.mp4",
        "herkes.mp4",
        "çok.mp4",
        "şaşırmak.mp4"
    ],
    "Küçük kız Doktor Levent’in kızıydı.": [
        "küçük.mp4",
        "kız.mp4",
        "doktor.mp4",
        "l.gif",
        "e.gif",
        "v.gif",
        "e.gif",
        "n.gif",
        "t.gif",
        "kız.mp4"
    ],
    "Doktor Levent:": [
        "doktor.mp4",
        "l.gif",
        "e.gif",
        "v.gif",
        "e.gif",
        "n.gif",
        "t.gif"
    ],
    "— Kızım korkma, iyi olacaksın.": [
        "kız.mp4",
        "korkmak.mp4",
        "iyi.mp4",
        "olmak.mp4"
    ],
    "Bu sırada Filiz’in annesi ve dedesi hastaneye geldi.": [
        "bu.mp4",
        "sıra.mp4",
        "f.gif",
        "i.gif",
        "l.gif",
        "i.gif",
        "z.gif",
        "anne.mp4",
        "ve.mp4",
        "dede.mp4",
        "hastane.mp4",
        "gelmek.mp4"
    ],
    "Odaya girdiler.": [
        "oda.mp4",
        "girmek.mp4"
    ],
    "Annesi Filiz’i gördü ve ona sarıldı.": [
        "anne.mp4",
        "f.gif",
        "i.gif",
        "l.gif",
        "i.gif",
        "z.gif",
        "görmek.mp4",
        "ve.mp4",
        "o.mp4",
        "sarmak.mp4"
    ],
    "Kocasını da odada gördü.": [
        "koca.mp4",
        "oda.mp4",
        "görmek.mp4"
    ],
    "— Merak etmeyin, Filiz’in durumu iyi.": [
        "merak_etmek.mp4",
        "f.gif",
        "i.gif",
        "l.gif",
        "i.gif",
        "z.gif",
        "durum.mp4",
        "iyi.mp4"
    ],
    "Biraz sonra eve gidebiliriz.": [
        "biraz.mp4",
        "sonra.mp4",
        "ev.mp4",
        "gitmek.mp4"
    ],
    "Onu çok iyi bir doktor tedavi etti.": [
        "o.mp4",
        "çok.mp4",
        "iyi.mp4",
        "bir.mp4",
        "doktor.mp4",
        "tedavi_etmek.gif"
    ],
    "Filiz’in annesi ve dedesi bunları duydular ve rahatladılar.": [
        "f.gif",
        "i.gif",
        "l.gif",
        "i.gif",
        "z.gif",
        "anne.mp4",
        "ve.mp4",
        "dede.mp4",
        "bu.mp4",
        "duymak.mp4",
        "ve.mp4",
        "rahatlamak.mp4"
    ],
    "Filiz de heyecanla kazayı anlatmaya başladı.": [
        "f.gif",
        "i.gif",
        "l.gif",
        "i.gif",
        "z.gif",
        "heyecan.mp4",
        "kaza.mp4",
        "anlamak.mp4",
        "başlamak.mp4"
    ]
}